LICENSE
README.md
setup.py
troykahat/__init__.py
troykahat/gpio_expander.py
troykahat/troykahat.py
troykahat.egg-info/PKG-INFO
troykahat.egg-info/SOURCES.txt
troykahat.egg-info/dependency_links.txt
troykahat.egg-info/requires.txt
troykahat.egg-info/top_level.txt