Metadata-Version: 2.1
Name: troykahat
Version: 1.0.0
Summary: Raspberry Pi library for interaction with a Amperka TroykaHAT.
Home-page: https://github.com/amperka/TroykaHatPython
Author: Amperka LLC
Author-email: igor@amperka.com
License: GPLv3
Platform: UNKNOWN
Classifier: Programming Language :: Python :: 3
Classifier: Programming Language :: Python :: 3.7
License-File: LICENSE
